{
  "Mission-Rec-Center-100": {
    "basketball": [
      [],
      [],
      [
        [
          540,
          1020
        ]
      ],
      [
        [
          540,
          1020
        ]
      ],
      [],
      [
        [
          540,
          1020
        ]
      ],
      [
        [
          540,
          1020
        ]
      ]
    ],
    "season": "Mission Rec Center Summer Schedule",
    "scrapedAt": "2026-06-19T01:48:10.616Z"
  },
  "Moscone-Rec-Center-101": {
    "basketball": [
      [],
      [],
      [
        [
          930,
          1020
        ]
      ],
      [
        [
          780,
          840
        ]
      ],
      [
        [
          930,
          1020
        ],
        [
          1020,
          1170
        ]
      ],
      [
        [
          780,
          840
        ]
      ],
      [
        [
          780,
          990
        ]
      ]
    ],
    "season": "Moscone Rec Center Summer Schedule",
    "scrapedAt": "2026-06-19T01:48:10.947Z"
  },
  "St-Marys-Rec-Center-109": {
    "basketball": [
      [],
      [],
      [
        [
          1050,
          1290
        ]
      ],
      [],
      [],
      [
        [
          1050,
          1290
        ]
      ],
      [
        [
          540,
          1020
        ]
      ]
    ],
    "season": "St. Mary's Rec Center Summer Schedule",
    "scrapedAt": "2026-06-19T01:48:11.306Z"
  },
  "Upper-Noe-Rec-Center-112": {
    "basketball": [
      [],
      [],
      [],
      [],
      [],
      [],
      [
        [
          540,
          720
        ]
      ]
    ],
    "season": "Upper Noe Rec Center Summer Schedule",
    "scrapedAt": "2026-06-19T01:48:11.655Z"
  },
  "Hamilton-Rec-Center-93": {
    "basketball": [
      [],
      [],
      [
        [
          930,
          1230
        ]
      ],
      [
        [
          930,
          1230
        ]
      ],
      [
        [
          930,
          1230
        ]
      ],
      [
        [
          930,
          1230
        ]
      ],
      [
        [
          570,
          990
        ]
      ]
    ],
    "season": "Hamilton Rec Center Summer Schedule",
    "scrapedAt": "2026-06-19T01:48:11.992Z"
  },
  "Eureka-Valley-Rec-Center-86": {
    "basketball": [
      [],
      [],
      [
        [
          540,
          660
        ],
        [
          1080,
          1200
        ]
      ],
      [],
      [
        [
          540,
          660
        ]
      ],
      [],
      []
    ],
    "season": "Eureka Valley Rec Center Summer Schedule",
    "scrapedAt": "2026-06-19T01:48:12.351Z"
  },
  "Richmond-Rec-Center-105": {
    "basketball": [
      [],
      [],
      [
        [
          1080,
          1425
        ]
      ],
      [
        [
          885,
          1245
        ]
      ],
      [
        [
          825,
          1050
        ]
      ],
      [
        [
          885,
          1245
        ]
      ],
      [
        [
          825,
          990
        ]
      ]
    ],
    "season": "Richmond Rec Center Summer Schedule",
    "scrapedAt": "2026-06-19T01:48:13.081Z"
  },
  "Sunset-Rec-Center-110": {
    "basketball": [
      [],
      [],
      [],
      [],
      [
        [
          1050,
          1260
        ]
      ],
      [
        [
          1050,
          1260
        ]
      ],
      []
    ],
    "season": "Sunset Rec Center Summer Schedule",
    "scrapedAt": "2026-06-19T01:48:13.426Z"
  },
  "Palega-Rec-Center-103": {
    "basketball": [
      [],
      [],
      [
        [
          600,
          960
        ]
      ],
      [
        [
          600,
          960
        ]
      ],
      [
        [
          600,
          960
        ],
        [
          720,
          930
        ]
      ],
      [
        [
          600,
          960
        ]
      ],
      [
        [
          540,
          600
        ],
        [
          600,
          660
        ],
        [
          690,
          750
        ]
      ]
    ],
    "season": "Palega Rec Center Summer Schedule",
    "scrapedAt": "2026-06-19T01:48:13.758Z"
  },
  "Joseph-Lee-Rec-Center-95": {
    "basketball": [
      [],
      [],
      [
        [
          600,
          1020
        ]
      ],
      [
        [
          600,
          1080
        ],
        [
          1080,
          1200
        ]
      ],
      [
        [
          600,
          1020
        ]
      ],
      [
        [
          600,
          1200
        ]
      ],
      [
        [
          840,
          990
        ]
      ]
    ],
    "season": "Joseph Lee Rec Center Summer Schedule",
    "scrapedAt": "2026-06-19T01:48:14.110Z"
  },
  "Minnie-Love-Ward-Rec-Center-97": {
    "basketball": [
      [],
      [],
      [],
      [
        [
          1125,
          1245
        ]
      ],
      [
        [
          960,
          1095
        ]
      ],
      [
        [
          960,
          1245
        ]
      ],
      [
        [
          630,
          750
        ],
        [
          765,
          1005
        ]
      ]
    ],
    "season": "Minnie & Lovie Ward Rec Center Summer Schedule",
    "scrapedAt": "2026-06-19T01:48:14.459Z"
  },
  "Bernal-Heights-Rec-Center-83": {
    "basketball": [
      [],
      [],
      [
        [
          780,
          1185
        ]
      ],
      [
        [
          1080,
          1200
        ],
        [
          600,
          1080
        ]
      ],
      [
        [
          780,
          1185
        ]
      ],
      [
        [
          600,
          1185
        ]
      ],
      [
        [
          615,
          1005
        ]
      ]
    ],
    "season": "Bernal Heights Rec Center Summer Schedule",
    "scrapedAt": "2026-06-19T01:48:14.805Z"
  },
  "Betty-Ann-Ong-Recreation-Center-84": {
    "basketball": [
      [],
      [],
      [
        [
          600,
          930
        ]
      ],
      [
        [
          600,
          840
        ]
      ],
      [
        [
          600,
          1230
        ]
      ],
      [
        [
          960,
          1230
        ]
      ],
      [
        [
          540,
          780
        ]
      ]
    ],
    "season": "Betty Ann Ong Chinese Rec Center Summer Schedule",
    "scrapedAt": "2026-06-19T01:48:15.117Z"
  },
  "Glen-Canyon-Park-Recreation-Center-89": {
    "basketball": [
      [],
      [],
      [
        [
          690,
          1080
        ]
      ],
      [
        [
          960,
          1080
        ]
      ],
      [
        [
          960,
          1170
        ]
      ],
      [
        [
          750,
          960
        ]
      ],
      [
        [
          750,
          900
        ],
        [
          900,
          1080
        ]
      ]
    ],
    "season": "Glen Canyon Rec Center Summer Schedule",
    "scrapedAt": "2026-06-19T01:48:15.463Z"
  },
  "Herz-Recreation-Center-471": {
    "basketball": [
      [],
      [],
      [
        [
          870,
          1185
        ]
      ],
      [
        [
          870,
          1245
        ]
      ],
      [
        [
          870,
          1245
        ]
      ],
      [
        [
          870,
          1245
        ]
      ],
      [
        [
          540,
          990
        ]
      ]
    ],
    "season": "Herz Rec Center Summer Schedule",
    "scrapedAt": "2026-06-19T01:48:15.822Z"
  },
  "Potrero-Hill-Rec-Center-275": {
    "basketball": [
      [],
      [],
      [
        [
          600,
          1170
        ]
      ],
      [
        [
          600,
          1020
        ]
      ],
      [
        [
          600,
          1020
        ]
      ],
      [
        [
          600,
          1170
        ]
      ],
      [
        [
          540,
          990
        ]
      ]
    ],
    "season": "Potrero Hill Rec Center Summer Schedule",
    "scrapedAt": "2026-06-19T01:48:16.157Z"
  }
}
